MLGeometry/__init__.py
MLGeometry/bihomoNN.py
MLGeometry/cicyhypersurface.py
MLGeometry/complex_math.py
MLGeometry/dataset.py
MLGeometry/hypersurface.py
MLGeometry/loss.py
MLGeometry/trainer.py
mlgeometry_jax-2.0.0.dist-info/licenses/LICENSE
mlgeometry_jax-2.0.0.dist-info/METADATA
mlgeometry_jax-2.0.0.dist-info/WHEEL
mlgeometry_jax-2.0.0.dist-info/top_level.txt
mlgeometry_jax-2.0.0.dist-info/RECORD
