Metadata-Version: 2.4
Name: MLGeometry-JAX
Version: 2.0.0
Summary: Higher dimensional computational geometry using machine learning software (JAX backend)
Maintainer-email: Yidi Qi <qiyidi2012@gmail.com>
License: MIT License
Project-URL: Homepage, https://github.com/yidiq7/MLGeometry
Project-URL: Changelog, https://github.com/yidiq7/MLGeometry/blob/main/CHANGELOG.md
Requires-Python: >=3.11
License-File: LICENSE
Requires-Dist: jax
Requires-Dist: flax
Requires-Dist: optax
Requires-Dist: jaxopt
Requires-Dist: sympy
Requires-Dist: matplotlib
Requires-Dist: mpmath
Requires-Dist: numpy
Dynamic: license-file
